VSRstats/__init__.py
VSRstats/frequency_domain.py
VSRstats/nonlinear.py
VSRstats/pars_rating.py
VSRstats/time_domain.py
VSRstats/tools.py
VSRstats-1.31.dist-info/METADATA
VSRstats-1.31.dist-info/WHEEL
VSRstats-1.31.dist-info/top_level.txt
VSRstats-1.31.dist-info/RECORD
